coronagraphoto/__init__.py
coronagraphoto/_version.py
coronagraphoto/constants.py
coronagraphoto/conversions.py
coronagraphoto/core/__init__.py
coronagraphoto/core/exposure.py
coronagraphoto/core/optical_elements.py
coronagraphoto/core/optical_path.py
coronagraphoto/core/simulation.py
coronagraphoto/core/sky_scene.py
coronagraphoto/core/sources.py
coronagraphoto/deprecated/__init__.py
coronagraphoto/deprecated/composite.py
coronagraphoto/deprecated/detector.py
coronagraphoto/deprecated/logger.py
coronagraphoto/deprecated/observation.py
coronagraphoto/deprecated/observations.py
coronagraphoto/deprecated/observing_scenario.py
coronagraphoto/deprecated/post_processing.py
coronagraphoto/deprecated/processing_config.py
coronagraphoto/deprecated/settings.py
coronagraphoto/deprecated/speckle_map.py
coronagraphoto/deprecated/util.py
coronagraphoto/loaders/__init__.py
coronagraphoto/loaders/exovista.py
coronagraphoto/optical_elements/__init__.py
coronagraphoto/optical_elements/coronagraph.py
coronagraphoto/optical_elements/detector.py
coronagraphoto/optical_elements/optical_filters.py
coronagraphoto/optical_elements/primary.py
coronagraphoto/optical_elements/throughput_elements.py
coronagraphoto/transforms/__init__.py
coronagraphoto/transforms/image_transforms.py
coronagraphoto/transforms/map_coordinates.py
coronagraphoto/transforms/orbital_mechanics.py
coronagraphoto/util/composite.py
coronagraphoto-2.2.0.dist-info/METADATA
coronagraphoto-2.2.0.dist-info/WHEEL
coronagraphoto-2.2.0.dist-info/licenses/LICENSE
coronagraphoto-2.2.0.dist-info/RECORD
