Metadata-Version: 2.4
Name: coronagraphoto
Version: 2.2.0
Summary: A python library to simulate coronagraphic observations of exoplanets.
Project-URL: Homepage, https://github.com/CoreySpohn/coronagraphoto
Project-URL: Issues, https://github.com/CoreySpohn/coronagraphoto/issues
Author-email: Corey Spohn <corey.a.spohn@nasa.gov>
License: MIT License
License-File: LICENSE
Classifier: Development Status :: 3 - Alpha
Classifier: Intended Audience :: Science/Research
Classifier: License :: OSI Approved :: MIT License
Classifier: Programming Language :: Python :: 3
Classifier: Topic :: Scientific/Engineering :: Astronomy
Requires-Python: >=3.9
Requires-Dist: astropy
Requires-Dist: equinox
Requires-Dist: interpax
Requires-Dist: jax
Requires-Dist: lod-unit
Requires-Dist: numpy
Requires-Dist: orbix
Requires-Dist: yippy
Provides-Extra: dev
Requires-Dist: pre-commit; extra == 'dev'
Requires-Dist: ruff; extra == 'dev'
Provides-Extra: docs
Requires-Dist: myst-parser; extra == 'docs'
Requires-Dist: sphinx; extra == 'docs'
Requires-Dist: sphinx-autoapi; extra == 'docs'
Requires-Dist: sphinx-autodoc-typehints; extra == 'docs'
Requires-Dist: sphinx-book-theme; extra == 'docs'
Provides-Extra: test
Requires-Dist: hypothesis; extra == 'test'
Requires-Dist: nox; extra == 'test'
Requires-Dist: pytest; extra == 'test'
Requires-Dist: pytest-cov; extra == 'test'
